jupyter_server_config.py
setup.py
etc/jupyter/jupyter_server_config.d/serve.json
serve/__init__.py
serve/__main__.py
serve/application.py
serve/handlers.py
serve/static/render-ui/222.9e2b8d463f9bedcb.js
serve/static/render-ui/227.3f1a8f5ca9e24b96.js
serve/static/render-ui/3rdpartylicenses.txt
serve/static/render-ui/482.a04576bbe1e9195c.js
serve/static/render-ui/5.c411a729ee201d46.js
serve/static/render-ui/625.121743b98d40ec89.js
serve/static/render-ui/750.10c07e8236842850.js
serve/static/render-ui/828.ca35a89bb5fc2cae.js
serve/static/render-ui/906.78eeb630ad2b9f79.js
serve/static/render-ui/941.a0ef451f387b9c4b.js
serve/static/render-ui/favicon.ico
serve/static/render-ui/index.html
serve/static/render-ui/main.76f44d98b6f2749c.js
serve/static/render-ui/polyfills.c4e865107f304558.js
serve/static/render-ui/runtime.cef9eee43e1134ff.js
serve/static/render-ui/styles.ab1d78fd50d9dfd6.css
serve/static/render-ui/assets/config.json
serve/templates/error.html
render_server_ext-0.1.0.data/data/etc/jupyter/jupyter_server_config.d/serve.json
render_server_ext-0.1.0.dist-info/METADATA
render_server_ext-0.1.0.dist-info/WHEEL
render_server_ext-0.1.0.dist-info/entry_points.txt
render_server_ext-0.1.0.dist-info/licenses/LICENSE
render_server_ext-0.1.0.dist-info/RECORD
